gcspath/__init__.py
gcspath/about.py
gcspath/api.py
gcspath/base.py
gcspath/client.py
gcspath/file.py
gcspath/gcs.py
gcspath/py.typed
tests/__init__.py
tests/conftest.py
tests/test_api.py
tests/test_base.py
tests/test_client.py
tests/test_package.py
gcspath-0.0.17.dist-info/LICENSE
gcspath-0.0.17.dist-info/METADATA
gcspath-0.0.17.dist-info/WHEEL
gcspath-0.0.17.dist-info/entry_points.txt
gcspath-0.0.17.dist-info/top_level.txt
gcspath-0.0.17.dist-info/RECORD
