Metadata-Version: 2.1
Name: gcspath
Version: 0.0.17
Summary: pathlib.Path subclasses for Google Cloud Storage
Home-page: https://github.com/justindujardin/gcspath
Author: Justin DuJardin
Author-email: justin@explosion.ai
License: Apache 2.0
Platform: UNKNOWN
Classifier: Development Status :: 4 - Beta
Classifier: Intended Audience :: Developers
Classifier: Natural Language :: English
Classifier: License :: OSI Approved :: Apache Software License
Classifier: Operating System :: OS Independent
Classifier: Programming Language :: Python
Classifier: Programming Language :: Python :: 3.6
Classifier: Programming Language :: Python :: 3.7
Classifier: Programming Language :: Python :: 3.8
Requires-Python: >= 3.6
Requires-Dist: google-cloud-storage (<2.0.0,>=1.26.0)
Requires-Dist: smart-open (==1.10.0)
